DESCRIPTION.rst
LICENSE
MANIFEST.in
README.md
setup.cfg
setup.py
oxford/__init__.py
oxford/base.py
oxford/emotion.py
oxford/face.py
oxford/facelist.py
oxford/person.py
oxford/persongroup.py
oxford/vision.py
oxford.egg-info/PKG-INFO
oxford.egg-info/SOURCES.txt
oxford.egg-info/dependency_links.txt
oxford.egg-info/top_level.txt
tests/__init__.py
tests/test_emotion.py
tests/test_face.py
tests/test_facelist.py
tests/test_person.py
tests/test_persongroup.py
tests/test_vision.py
tests/images/face-group.jpg
tests/images/face1.jpg
tests/images/face2.jpg
tests/images/vision.jpg