Metadata-Version: 1.1
Name: oxford
Version: 0.1.4
Summary: This project implements a client for the Project Oxford API's.
Home-page: https://github.com/irjudson/oxford
Author: Ivan R. Judson
Author-email: ivan.judson@microsoft.com
License: MIT
Download-URL: https://github.com/irjudson/oxford
Keywords: computer vision face detection linguistics language project oxford
Platform: UNKNOWN
Classifier: Development Status :: 4 - Beta
Classifier: Intended Audience :: Developers
Classifier: Topic :: Software Development :: Libraries :: Python Modules
Classifier: Operating System :: OS Independent
Classifier: License :: OSI Approved :: MIT License
Classifier: Programming Language :: Python :: 2.7
Classifier: Programming Language :: Python :: 3.4
